{"lib/fonts/Montserrat-Bold.ttf":["lib/fonts/Montserrat-Bold.ttf"],"lib/fonts/Montserrat-Regular.ttf":["lib/fonts/Montserrat-Regular.ttf"],"lib/fonts/Montserrat-SemiBold.ttf":["lib/fonts/Montserrat-SemiBold.ttf"],"lib/fonts/Nunito-Bold.ttf":["lib/fonts/Nunito-Bold.ttf"],"lib/fonts/Nunito-Light.ttf":["lib/fonts/Nunito-Light.ttf"],"lib/fonts/Nunito-Regular.ttf":["lib/fonts/Nunito-Regular.ttf"],"lib/images/appicon_img.png":["lib/images/appicon_img.png"],"lib/images/intro_img.gif":["lib/images/intro_img.gif"],"lib/images/login_img.png":["lib/images/login_img.png"],"lib/images/signup_img.png":["lib/images/signup_img.png"],"packages/cupertino_icons/assets/CupertinoIcons.ttf":["packages/cupertino_icons/assets/CupertinoIcons.ttf"]}